SymbSyntDec/__init__.py
SymbSyntDec/call_SymbSyntDec.py
SymbSyntDec/closure.py
SymbSyntDec/ground.py
SymbSyntDec/main.py
SymbSyntDec/modify.py
SymbSyntDec/past.py
SymbSyntDec/pastSimple.py
SymbSyntDec/snf.py
SymbSyntDec/state_variables.py
symbsyntdec-1.0.9.dist-info/METADATA
symbsyntdec-1.0.9.dist-info/WHEEL
symbsyntdec-1.0.9.dist-info/licenses/LICENSE
symbsyntdec-1.0.9.dist-info/RECORD
