Metadata-Version: 2.3
Name: SymbSyntDec
Version: 1.0.9
Summary: This package takes a symbolic DFA and produces an AIGER file of type aag
Project-URL: Homepage, https://github.com/danielaisen/SymbSyntDec
Project-URL: Issues, https://github.com/danielaisen/SymbSyntDec/issues
Author-email: Daniel Bachmann Aisen <danielmaxaisen@gmail.com>
License-File: LICENSE
Classifier: License :: OSI Approved :: MIT License
Classifier: Operating System :: OS Independent
Classifier: Programming Language :: Python :: 3
Requires-Python: >=3.8
Requires-Dist: pylogics-modalities
Requires-Dist: symdfa2aiger
